funnyone/__init__.py
funnyone-0.0.1.dist-info/LICENSE.txt
funnyone-0.0.1.dist-info/METADATA
funnyone-0.0.1.dist-info/WHEEL
funnyone-0.0.1.dist-info/top_level.txt
funnyone-0.0.1.dist-info/RECORD
