Metadata-Version: 2.1
Name: funnyone
Version: 0.0.1
Summary: The funnyone joke in the world
Home-page: http://github.com/storborg/funnyone
Author: Flying Circus
Author-email: cdchinmoy@gmail.com
License: MIT
Keywords: funny,funnyone,comedy
Platform: UNKNOWN
Classifier: Development Status :: 3 - Alpha
Classifier: Intended Audience :: Developers
Classifier: Topic :: Software Development :: Build Tools
Classifier: License :: OSI Approved :: MIT License
Classifier: Programming Language :: Python :: 3
Classifier: Programming Language :: Python :: 3.4
Classifier: Programming Language :: Python :: 3.5
Classifier: Programming Language :: Python :: 3.6
Requires-Dist: pandas
